phew/__init__.py
phew/dns.py
phew/logging.py
phew/server.py
phew/template.py
micropython_ccrighton_phew-0.0.5.dist-info/METADATA
micropython_ccrighton_phew-0.0.5.dist-info/WHEEL
micropython_ccrighton_phew-0.0.5.dist-info/top_level.txt
micropython_ccrighton_phew-0.0.5.dist-info/RECORD
