Metadata-Version: 2.1
Name: micropython-ccrighton-phew
Version: 0.0.5
Summary: A small webserver and templating library specifically designed for MicroPython on the Pico W.
Author: Jonathan Williamson - Pimoroni
Maintainer: Charlie Crighton
Maintainer-email: code@crighton.net.nz
License: MIT
Project-URL: GitHub, https://github.com/ccrighton/phew
Project-URL: Change Log, https://github.com/ccrighton/phew/blob/main/changelog.md
